sinto/__init__.py
sinto/addbarcodes.py
sinto/addtags.py
sinto/arguments.py
sinto/blocks.py
sinto/cli.py
sinto/constants.py
sinto/filterbarcodes.py
sinto/fragments.py
sinto/tagtoname.py
sinto/tagtorg.py
sinto/tagtotag.py
sinto/utils.py
sinto-0.10.1.dist-info/LICENSE
sinto-0.10.1.dist-info/METADATA
sinto-0.10.1.dist-info/WHEEL
sinto-0.10.1.dist-info/entry_points.txt
sinto-0.10.1.dist-info/top_level.txt
sinto-0.10.1.dist-info/RECORD
