Metadata-Version: 2.1
Name: sinto
Version: 0.10.1
Summary: Tools for single-cell data processing
Home-page: https://timoast.github.io/sinto/
Author: Tim Stuart
Author-email: tstuart@nygenome.org
License: MIT
Project-URL: Bug Tracker, https://github.com/timoast/sinto/issues
Classifier: Programming Language :: Python :: 3
Classifier: License :: OSI Approved :: MIT License
Classifier: Operating System :: OS Independent
Classifier: Intended Audience :: Science/Research
Requires-Python: >=3.8
License-File: LICENSE
Requires-Dist: pysam >=0.14
Requires-Dist: scipy
Requires-Dist: numpy
Requires-Dist: umi-tools
